gemseo_petsc/__init__.py
gemseo_petsc/linear_solvers/__init__.py
gemseo_petsc/linear_solvers/petsc_ksp.py
gemseo_petsc/linear_solvers/settings/__init__.py
gemseo_petsc/linear_solvers/settings/petsc_ksp_settings.py
gemseo_petsc/ode/__init__.py
gemseo_petsc/ode/ts_library.py
gemseo_petsc/ode/settings/__init__.py
gemseo_petsc/ode/settings/petsc_ts_settings.py
gemseo_petsc/problems/__init__.py
gemseo_petsc/problems/smooth_ode.py
gemseo_petsc/problems/vanderpol.py
gemseo_petsc/utils/__init__.py
gemseo_petsc/utils/conversion.py
gemseo_petsc-4.1.2.dist-info/licenses/LICENSE.txt
gemseo_petsc-4.1.2.dist-info/METADATA
gemseo_petsc-4.1.2.dist-info/WHEEL
gemseo_petsc-4.1.2.dist-info/entry_points.txt
gemseo_petsc-4.1.2.dist-info/top_level.txt
gemseo_petsc-4.1.2.dist-info/RECORD
