Metadata-Version: 2.4
Name: gemseo-petsc
Version: 4.1.2
Summary: PETSc GEMSEO interface.
Author-email: GEMSEO developers <contact@gemseo.org>
License-Expression: LGPL-3.0
Project-URL: Homepage, https://gemseo.org
Project-URL: Source, https://gitlab.com/gemseo/dev/gemseo-petsc
Project-URL: Issues, https://gitlab.com/gemseo/dev/gemseo-petsc/-/issues
Classifier: Intended Audience :: Science/Research
Classifier: Topic :: Scientific/Engineering
Classifier: Operating System :: POSIX :: Linux
Classifier: Operating System :: MacOS
Classifier: Operating System :: Microsoft :: Windows
Classifier: Programming Language :: Python :: 3 :: Only
Classifier: Programming Language :: Python :: 3.10
Classifier: Programming Language :: Python :: 3.11
Classifier: Programming Language :: Python :: 3.12
Classifier: Programming Language :: Python :: 3.13
Requires-Python: <3.14,>=3.10
License-File: LICENSE.txt
Requires-Dist: gemseo[all]<7,>=6.3
Requires-Dist: numpy
Requires-Dist: petsc4py<3.21,>=3
Requires-Dist: scipy
Dynamic: license-file
